hotAD/ADfun.py
hotAD/AutoDiffObject.py
hotAD/ElementaryFunctions.py
hotAD/__init__.py
hotAD-0.0.1.dist-info/LICENSE
hotAD-0.0.1.dist-info/METADATA
hotAD-0.0.1.dist-info/WHEEL
hotAD-0.0.1.dist-info/top_level.txt
hotAD-0.0.1.dist-info/RECORD
