Metadata-Version: 2.1
Name: hotAD
Version: 0.0.1
Summary: A Python package for forward mode automatic differentiation for multivariate functions, Jacobian/Hessian matrix computation, root-finding, and optimization routines.
Home-page: https://github.com/CS207ProjectGroup8/cs207-FinalProject
Author: Anthony Rentsch, Jiayin Lu, Lipika Ramaswamy, Yuanheng Wang
Author-email: anthony.rentsch@g.harvard.edu
License: UNKNOWN
Platform: UNKNOWN
Classifier: Programming Language :: Python :: 3
Classifier: License :: OSI Approved :: MIT License
Classifier: Operating System :: OS Independent
Requires-Dist: numpy (==1.15.2)
Requires-Dist: matplotlib (==2.2.3)
